MANIFEST.in
README.rst
setup.py
ckanext/__init__.py
ckanext/s3filestore/__init__.py
ckanext/s3filestore/commands.py
ckanext/s3filestore/controller.py
ckanext/s3filestore/plugin.py
ckanext/s3filestore/uploader.py
ckanext/s3filestore/tests/__init__.py
ckanext/s3filestore/tests/test_controller.py
ckanext/s3filestore/tests/test_uploader.py
ckanext_s3filestore.egg-info/PKG-INFO
ckanext_s3filestore.egg-info/SOURCES.txt
ckanext_s3filestore.egg-info/dependency_links.txt
ckanext_s3filestore.egg-info/entry_points.txt
ckanext_s3filestore.egg-info/pbr.json
ckanext_s3filestore.egg-info/top_level.txt