Metadata-Version: 1.1
Name: ckanext-s3filestore
Version: 0.0.3
Summary: Host resource files using Amazon Web Service's S3 storage
Home-page: https://github.com/okfn/ckanext-s3filestore
Author: Brook Elgie
Author-email: brook.elgie@okfn.org
License: AGPL
Keywords: CKAN S3 AWS
Platform: UNKNOWN
Classifier: Development Status :: 5 - Production/Stable
Classifier: License :: OSI Approved :: GNU Affero General Public License v3 or later (AGPLv3+)
Classifier: Programming Language :: Python :: 2.6
Classifier: Programming Language :: Python :: 2.7
